repoyard/__init__.py
repoyard/_models.py
repoyard/config.py
repoyard/const.py
repoyard/_cli/__init__.py
repoyard/_cli/app.py
repoyard/_cli/main.py
repoyard/_utils/__init__.py
repoyard/_utils/base.py
repoyard/_utils/logical_expressions.py
repoyard/_utils/rclone.py
repoyard/_utils/sync_helper.py
repoyard/cmds/__init__.py
repoyard/cmds/_create_user_symlinks.py
repoyard/cmds/_delete_repo.py
repoyard/cmds/_exclude_repo.py
repoyard/cmds/_get_repo_sync_status.py
repoyard/cmds/_include_repo.py
repoyard/cmds/_init_repoyard.py
repoyard/cmds/_modify_repometa.py
repoyard/cmds/_new_repo.py
repoyard/cmds/_sync_repo.py
repoyard/cmds/_sync_repometas.py
repoyard-0.1.7.dist-info/METADATA
repoyard-0.1.7.dist-info/WHEEL
repoyard-0.1.7.dist-info/entry_points.txt
repoyard-0.1.7.dist-info/licenses/LICENSE
repoyard-0.1.7.dist-info/RECORD
