Metadata-Version: 2.4
Name: repoyard
Version: 0.1.7
Summary: Add your description here
License-File: LICENSE
Requires-Python: >=3.11
Requires-Dist: pydantic>=2.12.4
Requires-Dist: python-ulid[pydantic]>=3.1.0
Requires-Dist: rich>=14.2.0
Requires-Dist: toml>=0.10.2
Requires-Dist: typer>=0.20.0
